minifysql-0.1.0.dist-info/METADATA
minifysql-0.1.0.dist-info/WHEEL
minifysql/__init__.py
minifysql/minifysql.cpython-313-darwin.so
minifysql-0.1.0.dist-info/RECORD
